crx_ism/__init__.py
crx_ism/evaluate.py
crx_ism/quality_metrics.py
crx_ism-0.0.7.dist-info/METADATA
crx_ism-0.0.7.dist-info/WHEEL
crx_ism-0.0.7.dist-info/top_level.txt
crx_ism-0.0.7.dist-info/RECORD
