Metadata-Version: 2.1
Name: crx_ism
Version: 0.0.7
Summary: image_sim
Author: ryukyungjoon
Author-email: ryuryukj6663@gmail.com
Classifier: Programming Language :: Python :: 3
Classifier: License :: OSI Approved :: MIT License
Classifier: Operating System :: OS Independent
Classifier: Operating System :: Microsoft :: Windows
Requires-Python: >=3.6
Requires-Dist: image-similarity-measures
